README.rst
setup.py
cjutils/__init__.py
cjutils/__main__.py
cjutils/_utils.py
cjutils/analyze.py
cjutils/cmd.py
cjutils/logger.py
cjutils/retry.py
cjutils/utils.py
cjutils.egg-info/PKG-INFO
cjutils.egg-info/SOURCES.txt
cjutils.egg-info/dependency_links.txt
cjutils.egg-info/top_level.txt
test/test.py