Metadata-Version: 1.0
Name: cjutils
Version: 0.0.23
Summary: cmd framework and utils
Home-page: https://github.com/CJYLZS/cjutils.git
Author: cjylzs
Author-email: 691086891@qq.com
License: MIT License
Keywords: cjutils
Platform: any
